github_download_counts/__init__.py
github_download_counts/github_download_counts.py
github_download_counts-1.1.0.dist-info/METADATA
github_download_counts-1.1.0.dist-info/WHEEL
github_download_counts-1.1.0.dist-info/entry_points.txt
github_download_counts-1.1.0.dist-info/licenses/LICENSE
github_download_counts-1.1.0.dist-info/RECORD
