Metadata-Version: 2.4
Name: github-download-counts
Version: 1.1.0
Summary: a simple Python wrapper around the GitHub REST API to get download counts for release assets and ghcr.io image pulls for organizations' repositories
Project-URL: Homepage, https://github.com/mmguero/github-download-counts
Project-URL: Issues, https://github.com/mmguero/github-download-counts/issues
Project-URL: Repository, https://github.com/mmguero/github-download-counts.git
Author-email: Seth Grover <mero.mero.guero@gmail.com>
License-File: LICENSE
Classifier: License :: OSI Approved :: MIT License
Classifier: Operating System :: OS Independent
Classifier: Programming Language :: Python :: 3
Requires-Python: >=3.6
Requires-Dist: beautifulsoup4==4.14.3
Requires-Dist: dateparser==1.2.2
Requires-Dist: github3-py==4.0.1
Requires-Dist: mmguero==2.0.4
